TempMail/Email.py
TempMail/Inbox.py
TempMail/TempMail.py
TempMail/__init__.py
tempmail_lol-3.0.0.dist-info/METADATA
tempmail_lol-3.0.0.dist-info/WHEEL
tempmail_lol-3.0.0.dist-info/top_level.txt
tempmail_lol-3.0.0.dist-info/RECORD
