Metadata-Version: 2.1
Name: tempmail-lol
Version: 3.0.0
Summary: A Python API for TempMail
Home-page: https://github.com/tempmail-lol/api-python
Author: Alexander Epolite, Alex Torres
Author-email: contact@bananacrumbs.us
Maintainer: Alexander Epolite
Maintainer-email: contact@bananacrumbs.us
Keywords: tempmail,api,lol,tempmail-lol,tempmail.lol,email,free
Classifier: Development Status :: 5 - Production/Stable
Classifier: Intended Audience :: Developers
Classifier: Programming Language :: Python :: 3
Classifier: Operating System :: Unix
Classifier: Operating System :: MacOS :: MacOS X
Classifier: Operating System :: Microsoft :: Windows
Requires-Dist: requests
